mate/__init__.py
mate/alerts.py
mate/checks.py
mate/db.py
mate/generators.py
mate/reports.py
mate/run.py
mate/stats.py
tests/__init__.py
tests/integration/__init__.py
tests/integration/conftest.py
tests/integration/test_generators.py
tests/integration/test_reports.py
tests/integration/test_run.py
tests/unit/__init__.py
tests/unit/conftest.py
tests/unit/test_checks.py
tests/unit/test_generators.py
running_mate-0.0.6.dist-info/METADATA
running_mate-0.0.6.dist-info/WHEEL
running_mate-0.0.6.dist-info/top_level.txt
running_mate-0.0.6.dist-info/RECORD
